hanashiai/__init__.py
hanashiai/core/__init__.py
hanashiai/core/exceptions.py
hanashiai/core/interfaces.py
hanashiai/core/models.py
hanashiai_core-0.5.0.dist-info/METADATA
hanashiai_core-0.5.0.dist-info/RECORD
hanashiai_core-0.5.0.dist-info/WHEEL
hanashiai_core-0.5.0.dist-info/top_level.txt
