Metadata-Version: 2.1
Name: hanashiai-core
Version: 0.5.0
Summary: Reddit API interface for Hanashiai
Home-page: http://www.kerneweksoftware.com/software.html
Author: Trevalyan Stevens
Author-email: etstevens60@gmail.com
License: MIT
Platform: UNKNOWN
Classifier: Programming Language :: Python
Classifier: Programming Language :: Python :: 3
Classifier: License :: OSI Approved :: MIT License
Classifier: Operating System :: OS Independent
Classifier: Development Status :: 3 - Alpha
Classifier: Intended Audience :: Developers
Classifier: Topic :: Software Development :: Libraries
Classifier: Topic :: Software Development :: Libraries :: Python Modules
Requires-Dist: praw (==5.4.0)
